whitebox_plugin_flight_management/pyproject.toml
whitebox_plugin_flight_management/__init__.py
whitebox_plugin_flight_management/apps.py
whitebox_plugin_flight_management/handlers/__init__.py
whitebox_plugin_flight_management/handlers/flights.py
whitebox_plugin_flight_management/handlers/key_moments.py
whitebox_plugin_flight_management/jsx/FlightPlanOverlay.jsx
whitebox_plugin_flight_management/jsx/FlightServiceComponent.jsx
whitebox_plugin_flight_management/jsx/FlightServiceComponent.test.jsx
whitebox_plugin_flight_management/jsx/TriggerButton.jsx
whitebox_plugin_flight_management/jsx/TriggerButton.test.jsx
whitebox_plugin_flight_management/jsx/components/airport/AirportSearchInput.jsx
whitebox_plugin_flight_management/jsx/components/airport/AirportSearchInput.test.jsx
whitebox_plugin_flight_management/jsx/components/flight-plan/FlightPlan.jsx
whitebox_plugin_flight_management/jsx/components/flight-plan/FlightPlan.test.jsx
whitebox_plugin_flight_management/jsx/components/flight-plan/LocationInput.jsx
whitebox_plugin_flight_management/jsx/components/flight-plan/LocationInput.test.jsx
whitebox_plugin_flight_management/jsx/components/flight-plan/WaypointInput.jsx
whitebox_plugin_flight_management/jsx/components/flight-plan/WaypointInput.test.jsx
whitebox_plugin_flight_management/jsx/components/wizard/StartFlightWizard.jsx
whitebox_plugin_flight_management/jsx/components/wizard/StepIntro.jsx
whitebox_plugin_flight_management/jsx/components/wizard/StepIntro.test.jsx
whitebox_plugin_flight_management/jsx/components/wizard/steps/FlightPlanStep.jsx
whitebox_plugin_flight_management/jsx/components/wizard/steps/FlightPlanStep.test.jsx
whitebox_plugin_flight_management/jsx/components/wizard/steps/InstalledDevicesStep.jsx
whitebox_plugin_flight_management/jsx/components/wizard/steps/PreviewConnectedDevicesStep.jsx
whitebox_plugin_flight_management/jsx/components/wizard/steps/PreviewConnectedDevicesStep.test.jsx
whitebox_plugin_flight_management/jsx/stores/flight_plan.js
whitebox_plugin_flight_management-0.1.16.dist-info/LICENSE
whitebox_plugin_flight_management-0.1.16.dist-info/METADATA
whitebox_plugin_flight_management-0.1.16.dist-info/WHEEL
whitebox_plugin_flight_management-0.1.16.dist-info/entry_points.txt
whitebox_plugin_flight_management-0.1.16.dist-info/RECORD
