Metadata-Version: 2.3
Name: whitebox-plugin-flight-management
Version: 0.1.16
Summary: A plugin for whitebox to manage flight operations
License: GNU Affero General Public License v3
Author: Milos
Author-email: hello@klined.org
Requires-Python: >=3.10.0
Classifier: License :: Other/Proprietary License
Classifier: Programming Language :: Python :: 3
Classifier: Programming Language :: Python :: 3.10
Classifier: Programming Language :: Python :: 3.11
Classifier: Programming Language :: Python :: 3.12
Classifier: Programming Language :: Python :: 3.13
Requires-Dist: requests (>=2.32.5,<3.0.0)
